CHANGELOG
LICENSE
MANIFEST.in
WAIVER
WAIVER.asc
requirements.txt
setup.cfg
setup.py
test_requirements.txt
eth_erc20/__init__.py
eth_erc20/erc20.py
eth_erc20.egg-info/PKG-INFO
eth_erc20.egg-info/SOURCES.txt
eth_erc20.egg-info/dependency_links.txt
eth_erc20.egg-info/entry_points.txt
eth_erc20.egg-info/requires.txt
eth_erc20.egg-info/top_level.txt
eth_erc20/data/ERC20.json
eth_erc20/runnable/balance.py
eth_erc20/runnable/info.py
eth_erc20/runnable/transfer.py
eth_erc20/unittest/__init__.py
eth_erc20/unittest/base.py
giftable_erc20_token/__init__.py
giftable_erc20_token/factory.py
giftable_erc20_token/gen.py
giftable_erc20_token/data/.chainlib
giftable_erc20_token/data/GiftableToken.bin
giftable_erc20_token/data/GiftableToken.json
giftable_erc20_token/data/__init__.py
giftable_erc20_token/runnable/gift.py
giftable_erc20_token/runnable/minter.py
giftable_erc20_token/runnable/publish.py
giftable_erc20_token/unittest/__init__.py
giftable_erc20_token/unittest/base.py
static_token/data/StaticToken.bin
static_token/data/StaticToken.json
static_token/data/__init__.py
tests/test_erc20_interface.py
tests/test_giftable.py
tests/test_static.py