Metadata-Version: 2.1
Name: eth-erc20
Version: 0.9.0
Summary: ERC20 interface and simple contract with deployment script that lets any address mint and gift itself tokens.
Home-page: https://git.defalsify.org/eth-erc20
Author: Louis Holbrook
Author-email: dev@holbrook.no
License: AGPLv3+
Keywords: dlt,ethereum,token,blockchain,cryptocurrency
Classifier: Programming Language :: Python :: 3
Classifier: Operating System :: OS Independent
Classifier: Development Status :: 4 - Beta
Classifier: Environment :: Console
Classifier: Intended Audience :: Developers
Classifier: License :: OSI Approved :: GNU Affero General Public License v3 or later (AGPLv3+)
Classifier: Topic :: Internet
Classifier: Topic :: Software Development :: Libraries
Requires-Python: >=3.8
License-File: LICENSE
Requires-Dist: confini~=0.6.1
Requires-Dist: chainlib-eth~=0.6.0
Requires-Dist: chainlib~=0.5.0
Requires-Dist: potaahto~=0.1.1
